nonebot_plugin_chatglm/__init__.py
nonebot_plugin_chatglm/chat.py
nonebot_plugin_chatglm/config.py
nonebot_plugin_chatglm/prompt.py
nonebot_plugin_chatglm/utils.py
nonebot_plugin_chatglm-0.1.6.dist-info/WHEEL
nonebot_plugin_chatglm-0.1.6.dist-info/METADATA
nonebot_plugin_chatglm-0.1.6.dist-info/licenses/LICENSE
nonebot_plugin_chatglm-0.1.6.dist-info/RECORD
