Metadata-Version: 2.1
Name: nonebot-plugin-chatglm
Version: 0.1.6
Summary: 基于ChatGLM-6B的NoneBot2插件
License: MIT
Author-email: dao_mingze <dao_mingze@163.com>
Requires-Python: >=3.8
Requires-Dist: cpm-kernels>=1.0.11
Requires-Dist: icetk>=0.0.4
Requires-Dist: nonebot-adapter-onebot>=2.2.0
Requires-Dist: nonebot2>=2.0.0rc4
Requires-Dist: protobuf>=3.18.3
Requires-Dist: transformers>=4.27.1
Project-URL: repository, https://github.com/DaoMingze/zhukebot/tree/main/zhukebot/plugins/chatglm
